Workbook

Sheet 说明
B2: 成本试算与营运表格 · 使用说明
B4: 1. 蓝色字 + 黄色底 的格子 = 你要填/可以改的数字（进货价、售价、费用）。其他格子全是公式，不要动。
B5: 2. 先到「原料价格」把每项换成你的真实进货价，「SKU成本卡」和「保本线」会自动重算。
B6: 3. 「SKU成本卡」看两个数：Food Cost % 超过 35% 的套装要么提价、要么减料。
B7: 4. 「保本线」告诉你：档口每天至少卖多少单、餐车一场至少做多少营业额才不亏。
B8: 5. 「餐车单日P&L」每场收车 15 分钟内填完；「场地评分档」同场累计 2 次 C 级就拉黑该场地。
B9: 6. 当前所有价格为估算占位值（来源：本计划书 01 文档的市场估价，2026-08），务必换成真实值后再做定价决策。

Sheet 原料价格
A1: 原料价格表（全部换成你的真实进货价）
A3: 项目 | B3: 单位 | C3: 单价 | D3: 备注
A4: 无骨鸡腿肉 | B4: /kg | C4: 15 | D4: 去骨腿肉，按批发价
A5: 腌料成本 | B5: /kg鸡 | C5: 1.2 | D5: 特别腌制配方，按每公斤鸡摊算
A6: 粉浆/炸粉 | B6: /kg鸡 | C6: 1.5 | D6: 两次裹粉用量摊算
A7: 炸油损耗 | B7: /kg鸡 | C7: 1 | D7: 含中央厨房一炸+前线二炸
A8: 鸭屎香芥末酱 | B8: /kg | C8: 22 | D8: 独家招牌，不外卖配方
A9: 火鸡面酱 | B9: /kg | C9: 12 | D9: 现有配方
A10: 原味芝士酱 | B10: /kg | C10: 16
A11: 麻辣芝士酱 | B11: /kg | C11: 17
A12: 松露芝士酱 | B12: /kg | C12: 25
A13: 椒盐粉 | B13: /kg | C13: 10
A14: 麻辣粉 | B14: /kg | C14: 14
A15: 甘梅粉 | B15: /kg | C15: 18
A16: 黑松露粉 | B16: /kg | C16: 60 | D16: premium 撒粉
A17: 炸蒜酥 | B17: /kg | C17: 18
A18: 炸葱头酥 | B18: /kg | C18: 16
A19: 辣椒干 | B19: /kg | C19: 12
A20: 咖喱叶(炸后) | B20: /kg | C20: 8
A21: 包装(杯+签+袋) | B21: /份 | C21: 0.6
A22: 自制饮料成本 | B22: /杯 | C22: 0.8 | D22: 糖浆+杯+冰摊算

Sheet SKU成本卡
A1: SKU 成本卡（M 杯 · 生肉 220g）— 改「原料价格」或黄色格，其余自动算
A3: 用量假设（可改）
A4: 鸡肉用量 kg/杯(M) | B4: 0.22
A5: 酱用量 kg/杯 | B5: 0.04
A6: 粉用量 kg/杯 | B6: 0.005
A7: 配料用量 kg/样 | B7: 0.01
A9: 鸡底成本/杯(M) = | B9: =$B$4*(SUM(原料价格!C4:C7)) -> 4.114 | C9: 鸡肉+腌料+粉浆+油耗 合计单价 × 用量
A11: 套装 | B11: 鸡底 | C11: 酱 | D11: 粉 | E11: 配料 | F11: 包装 | G11: 总成本 | H11: 售价 | I11: Food Cost % | J11: 毛利/杯 | K11: 日销(杯) | L11: 日毛利
A12: 招牌鸭屎香芥末鸡 | B12: =$B$9 -> 4.114 | C12: =$B$5*原料价格!C8 -> 0.88 | D12: 0 | E12: =$B$7*原料价格!C18 -> 0.16 | F12: =原料价格!C21 -> 0.6 | G12: =SUM(B12:F12) -> 5.754 | H12: 15.9 | I12: =IF(H12=0,0,G12/H12) -> 0.36188679 | J12: =H12-G12 -> 10.146 | K12: 25 | L12: =J12*K12 -> 253.65
A13: 火鸡面芝士鸡(双酱) | B13: =$B$9 -> 4.114 | C13: =$B$5*(原料价格!C9+原料价格!C10) -> 1.12 | D13: 0 | E13: 0 | F13: =原料价格!C21 -> 0.6 | G13: =SUM(B13:F13) -> 5.834 | H13: 17.9 | I13: =IF(H13=0,0,G13/H13) -> 0.32592179 | J13: =H13-G13 -> 12.066 | K13: 30 | L13: =J13*K13 -> 361.98
A14: 黑松露芝士鸡 | B14: =$B$9 -> 4.114 | C14: =$B$5*原料价格!C12 -> 1 | D14: =$B$6*原料价格!C16 -> 0.3 | E14: 0 | F14: =原料价格!C21 -> 0.6 | G14: =SUM(B14:F14) -> 6.014 | H14: 18.9 | I14: =IF(H14=0,0,G14/H14) -> 0.31820106 | J14: =H14-G14 -> 12.886 | K14: 12 | L14: =J14*K14 -> 154.632
A15: 麻辣香脆鸡 | B15: =$B$9 -> 4.114 | C15: 0 | D15: =$B$6*原料价格!C14 -> 0.07 | E15: =$B$7*(原料价格!C17+原料价格!C19+原料价格!C20) -> 0.38 | F15: =原料价格!C21 -> 0.6 | G15: =SUM(B15:F15) -> 5.164 | H15: 14.9 | I15: =IF(H15=0,0,G15/H15) -> 0.34657718 | J15: =H15-G15 -> 9.736 | K15: 20 | L15: =J15*K15 -> 194.72
A16: 甘梅古早味 | B16: =$B$9 -> 4.114 | C16: 0 | D16: =$B$6*原料价格!C15 -> 0.09 | E16: 0 | F16: =原料价格!C21 -> 0.6 | G16: =SUM(B16:F16) -> 4.804 | H16: 12.9 | I16: =IF(H16=0,0,G16/H16) -> 0.3724031 | J16: =H16-G16 -> 8.096 | K16: 15 | L16: =J16*K16 -> 121.44
A17: 饮料(combo 加购) | B17: 0 | C17: 0 | D17: 0 | E17: 0 | F17: =原料价格!C22 -> 0.8 | G17: =SUM(B17:F17) -> 0.8 | H17: 2.9 | I17: =IF(H17=0,0,G17/H17) -> 0.27586207 | J17: =H17-G17 -> 2.1 | K17: 60 | L17: =J17*K17 -> 126
A18: 合计 / 加权 | I18: =SUMPRODUCT(G12:G17,K12:K17)/SUMPRODUCT(H12:H17,K12:K17) -> 0.33631377 | K18: =SUM(K12:K17) -> 162 | L18: =SUM(L12:L17) -> 1212.422
A20: 加权综合毛利率 = | B20: =1-I18 -> 0.66368623 | C20: ← 保本线用这个数

Sheet 保本线
A1: 保本线计算（黄色格填真实费用）
A3: ① 档口（月度）
A4: 月租金 | B4: 4500
A5: 月人工 | B5: 6000
A6: 月水电杂费 | B6: 1200
A7: 月固定成本合计 | B7: =SUM(B4:B6) -> 11700
A8: 综合毛利率(自 SKU成本卡) | B8: =SKU成本卡!$B$20 -> 0.66368623
A9: 平均客单价(估) | B9: 17
A10: 月保本营业额 | B10: =IF(B8=0,0,B7/B8) -> 17628.812
A11: 日保本单量(按30天) | B11: =IF(B9=0,0,B10/30/B9) -> 34.566299 | C11: ← 每天卖不到这个数就是亏，贴在档口后台
A14: ② 餐车（单场）
A15: 摊位费 | B15: 250
A16: 人工(2人) | B16: 200
A17: 油/气/车耗 | B17: 80
A18: 单场固定成本 | B18: =SUM(B15:B17) -> 530
A19: 综合毛利率(自 SKU成本卡) | B19: =SKU成本卡!$B$20 -> 0.66368623
A20: 保本营业额/场 | B20: =IF(B19=0,0,B18/B19) -> 798.57013
A21: 保本单量/场 | B21: =IF($B$9=0,0,B20/$B$9) -> 46.974714
A22: Go/No-Go 线(保本×1.5) | B22: =B20*1.5 -> 1197.8552 | C22: ← 预估营业额低于这个数的场，不出车

Sheet 餐车单日P&L
A1: 餐车单日 P&L（每场收车 15 分钟内填，第 4 行是示例）
A3: 日期 | B3: 场地 | C3: 天气 | D3: 营业额 | E3: 单量 | F3: 客单价 | G3: 货成本 | H3: 摊位费 | I3: 人工 | J3: 油气杂费 | K3: 当日净利 | L3: 净利率 | M3: 备注
A4: 2026-08-15 | B4: 示例夜市 | C4: 晴 | D4: 1580 | E4: 96 | F4: =IF(E4=0,0,D4/E4) -> 16.458333 | G4: =D4*(1-SKU成本卡!$B$20) -> 531.37576 | H4: 250 | I4: 200 | J4: 80 | K4: =D4-G4-H4-I4-J4 -> 518.62424 | L4: =IF(D4=0,0,K4/D4) -> 0.32824319 | M4: 示例行：填法参考，可删除
F5: =IF(E5=0,0,D5/E5) -> 0 | G5: =IF(D5=0,0,D5*(1-SKU成本卡!$B$20)) -> 0 | K5: =IF(D5=0,0,D5-G5-H5-I5-J5) -> 0 | L5: =IF(D5=0,0,K5/D5) -> 0
F6: =IF(E6=0,0,D6/E6) -> 0 | G6: =IF(D6=0,0,D6*(1-SKU成本卡!$B$20)) -> 0 | K6: =IF(D6=0,0,D6-G6-H6-I6-J6) -> 0 | L6: =IF(D6=0,0,K6/D6) -> 0
F7: =IF(E7=0,0,D7/E7) -> 0 | G7: =IF(D7=0,0,D7*(1-SKU成本卡!$B$20)) -> 0 | K7: =IF(D7=0,0,D7-G7-H7-I7-J7) -> 0 | L7: =IF(D7=0,0,K7/D7) -> 0
F8: =IF(E8=0,0,D8/E8) -> 0 | G8: =IF(D8=0,0,D8*(1-SKU成本卡!$B$20)) -> 0 | K8: =IF(D8=0,0,D8-G8-H8-I8-J8) -> 0 | L8: =IF(D8=0,0,K8/D8) -> 0
F9: =IF(E9=0,0,D9/E9) -> 0 | G9: =IF(D9=0,0,D9*(1-SKU成本卡!$B$20)) -> 0 | K9: =IF(D9=0,0,D9-G9-H9-I9-J9) -> 0 | L9: =IF(D9=0,0,K9/D9) -> 0
F10: =IF(E10=0,0,D10/E10) -> 0 | G10: =IF(D10=0,0,D10*(1-SKU成本卡!$B$20)) -> 0 | K10: =IF(D10=0,0,D10-G10-H10-I10-J10) -> 0 | L10: =IF(D10=0,0,K10/D10) -> 0
F11: =IF(E11=0,0,D11/E11) -> 0 | G11: =IF(D11=0,0,D11*(1-SKU成本卡!$B$20)) -> 0 | K11: =IF(D11=0,0,D11-G11-H11-I11-J11) -> 0 | L11: =IF(D11=0,0,K11/D11) -> 0
F12: =IF(E12=0,0,D12/E12) -> 0 | G12: =IF(D12=0,0,D12*(1-SKU成本卡!$B$20)) -> 0 | K12: =IF(D12=0,0,D12-G12-H12-I12-J12) -> 0 | L12: =IF(D12=0,0,K12/D12) -> 0
F13: =IF(E13=0,0,D13/E13) -> 0 | G13: =IF(D13=0,0,D13*(1-SKU成本卡!$B$20)) -> 0 | K13: =IF(D13=0,0,D13-G13-H13-I13-J13) -> 0 | L13: =IF(D13=0,0,K13/D13) -> 0
F14: =IF(E14=0,0,D14/E14) -> 0 | G14: =IF(D14=0,0,D14*(1-SKU成本卡!$B$20)) -> 0 | K14: =IF(D14=0,0,D14-G14-H14-I14-J14) -> 0 | L14: =IF(D14=0,0,K14/D14) -> 0
F15: =IF(E15=0,0,D15/E15) -> 0 | G15: =IF(D15=0,0,D15*(1-SKU成本卡!$B$20)) -> 0 | K15: =IF(D15=0,0,D15-G15-H15-I15-J15) -> 0 | L15: =IF(D15=0,0,K15/D15) -> 0
F16: =IF(E16=0,0,D16/E16) -> 0 | G16: =IF(D16=0,0,D16*(1-SKU成本卡!$B$20)) -> 0 | K16: =IF(D16=0,0,D16-G16-H16-I16-J16) -> 0 | L16: =IF(D16=0,0,K16/D16) -> 0
... F24: =IF(E24=0,0,D24/E24) -> 0 | G24: =IF(D24=0,0,D24*(1-SKU成本卡!$B$20)) -> 0 | K24: =IF(D24=0,0,D24-G24-H24-I24-J24) -> 0 | L24: =IF(D24=0,0,K24/D24) -> 0
A26: 货成本按「SKU成本卡」加权 food cost 自动估算；月底用实际进货对账修正。

Sheet 场地评分档
A1: 场地评分档（同场地连续 2 次 C = 拉黑；排期永远优先 A 场）
A3: 场地 | B3: 日期 | C3: 天气 | D3: 摊位费 | E3: 营业额 | F3: 单量 | G3: 当日净利 | H3: 评分 | I3: 备注/情报
A4: 示例夜市 | B4: 2026-08-15 | C4: 晴 | D4: 250 | E4: 1580 | F4: 96 | G4: 655 | H4: =IF(G4="","",IF(G4>=400,"A",IF(G4>=200,"B","C"))) -> A | I4: 示例行：净利自动评分，可删除
H5: =IF(G5="","",IF(G5>=400,"A",IF(G5>=200,"B","C")))
H6: =IF(G6="","",IF(G6>=400,"A",IF(G6>=200,"B","C")))
H7: =IF(G7="","",IF(G7>=400,"A",IF(G7>=200,"B","C")))
H8: =IF(G8="","",IF(G8>=400,"A",IF(G8>=200,"B","C")))
H9: =IF(G9="","",IF(G9>=400,"A",IF(G9>=200,"B","C")))
H10: =IF(G10="","",IF(G10>=400,"A",IF(G10>=200,"B","C")))
H11: =IF(G11="","",IF(G11>=400,"A",IF(G11>=200,"B","C")))
H12: =IF(G12="","",IF(G12>=400,"A",IF(G12>=200,"B","C")))
H13: =IF(G13="","",IF(G13>=400,"A",IF(G13>=200,"B","C")))
H14: =IF(G14="","",IF(G14>=400,"A",IF(G14>=200,"B","C")))
H15: =IF(G15="","",IF(G15>=400,"A",IF(G15>=200,"B","C")))
H16: =IF(G16="","",IF(G16>=400,"A",IF(G16>=200,"B","C")))
... H24: =IF(G24="","",IF(G24>=400,"A",IF(G24>=200,"B","C")))
A26: 评分标准：净利 ≥ RM400 = A；RM200–400 = B；< RM200 = C（标准可按你成本调整）
